cythonconst/__init__.py
cythonconst/plus.c
cythonconst/plus.cpython-311-darwin.so
cythonconst/plus.pyx
cythonconst-1.1.0.dist-info/METADATA
cythonconst-1.1.0.dist-info/WHEEL
cythonconst-1.1.0.dist-info/top_level.txt
cythonconst-1.1.0.dist-info/RECORD
