Metadata-Version: 2.1
Name: cythonconst
Version: 1.1.0
Summary: An example client with const in Cython
Requires-Python: >=3.11
Requires-Dist: libcythonconst
